oanda_bot/__init__.py
oanda_bot/oanda_bot.py
oanda_bot-0.1.2.dist-info/LICENSE.txt
oanda_bot-0.1.2.dist-info/METADATA
oanda_bot-0.1.2.dist-info/WHEEL
oanda_bot-0.1.2.dist-info/top_level.txt
oanda_bot-0.1.2.dist-info/RECORD
